__init__.py
colorlite.py
colorlite-0.0.2.dist-info/LICENSE
colorlite-0.0.2.dist-info/METADATA
colorlite-0.0.2.dist-info/WHEEL
colorlite-0.0.2.dist-info/top_level.txt
colorlite-0.0.2.dist-info/RECORD
